lc.py
uniref/__init__.py
uniref/platforms.py
uniref/bin/android/agent.js
uniref/bin/win/getproc32.exe
uniref/bin/win/getproc64.exe
uniref/bin/win/util64.dll
uniref/define/__init__.py
uniref/define/constant.py
uniref/define/patch.py
uniref/define/struct.py
uniref/define/types.py
uniref/mono/__init__.py
uniref/mono/assets.py
uniref/mono/component.py
uniref/mono/injector/__init__.py
uniref/mono/injector/android.py
uniref/mono/injector/interface.py
uniref/mono/injector/windows.py
uniref/util/__init__.py
uniref/util/compiler.py
uniref/util/disasm.py
uniref/util/scanner.py
uniref/util/winapi.py
uniref/util/injector/__init__.py
uniref/util/injector/android.py
uniref/util/injector/interface.py
uniref/util/injector/windows.py
uniref-0.5.2.dist-info/LICENSE
uniref-0.5.2.dist-info/METADATA
uniref-0.5.2.dist-info/WHEEL
uniref-0.5.2.dist-info/top_level.txt
uniref-0.5.2.dist-info/RECORD
