Metadata-Version: 2.1
Name: uniref
Version: 0.5.2
Summary: Unity reflection framework
Author-email: in1t <in1t@foxmail.com>
License: GNU AFFERO GENERAL PUBLIC LICENSE
Project-URL: Homepage, https://github.com/in1nit1t/uniref
Project-URL: Bug Tracker, https://github.com/in1nit1t/uniref/issues
Keywords: Unity,mono,il2cpp,reflection,patch,android,windows
Classifier: Development Status :: 4 - Beta
Classifier: Intended Audience :: Developers
Classifier: Programming Language :: Python :: 3.7
Classifier: Programming Language :: Python :: 3.8
Classifier: Programming Language :: Python :: 3.9
Classifier: Programming Language :: Python :: 3.10
Classifier: Programming Language :: Python :: 3.11
Classifier: Topic :: Software Development :: Libraries :: Python Modules
Classifier: License :: OSI Approved :: GNU Affero General Public License v3
Requires-Python: >=3.7
License-File: LICENSE
Requires-Dist: pywin32
Requires-Dist: capstone
Requires-Dist: keystone-engine
Requires-Dist: frida >=15.0.0
Requires-Dist: frida-tools >=10.0.0
